Metadata-Version: 2.1
Name: convmodel
Version: 0.3.0
Summary: convmodel provides a conversation model based on decoders models.
Home-page: https://github.com/colorfulscoop/convmodel
Author: Colorful Scoop
License: UNKNOWN
Platform: UNKNOWN
Classifier: Programming Language :: Python :: 3.8
Classifier: License :: OSI Approved :: MIT License
Classifier: Operating System :: OS Independent
Provides-Extra: cli
Provides-Extra: test
